{
  "Reviews": [
    {
      "Ratings": {
        "Service": 5.0,
        "Cleanliness": 4.0,
        "Overall": 5.0,
        "Value": 4.0,
        "Sleep Quality": 4.0,
        "Rooms": 4.0,
        "Location": 5.0
      },
      "AuthorLocation": "Los Altos, CA",
      "Title": "\u201cNice, private, romantic getaway\u201d",
      "Author": "Geoff_Los_Altos_CA",
      "ReviewID": "UR127828046",
      "Content": "wife avery nice 3night stay larger king recommend table chairs porch overlooking little onproperty vineyard 12 rows vines located northern tip napa town feels secluded hwy 29 10 mins yountville 20 st helena la residence owner hall nice wine tasting night 67pm theyll pour drink nice assortment cheeses breakfast cereals breadspastries fruit yogurt oatmeal woman breakfast buffet sweet attentive guest reheat tea woman fresh cup tea",
      "Date": "2012-04-13 00:00:00"
    },
    {
      "Ratings": {
        "Service": 5.0,
        "Cleanliness": 5.0,
        "Overall": 5.0,
        "Value": 5.0,
        "Sleep Quality": 5.0,
        "Rooms": 5.0,
        "Location": 5.0
      },
      "AuthorLocation": "California",
      "Title": "\u201cBeautiful Place in Napa\u201d",
      "Author": "SdR08",
      "ReviewID": "UR127220324",
      "Content": "checked 20 la residence little stay bathroom 20 upstairs main building stairs landing enjoyed stay monday wednesday feels cozy breakfast included pastries coffee variety juices restaurant italian restaurant walking distance bistro san excellent stay drive napa enjoyed stay staff friendly stay la residence clean care grounds",
      "Date": "2012-04-03 00:00:00"
    },
    {
      "Ratings": {
        "Service": 3.0,
        "Cleanliness": 5.0,
        "Overall": 4.0,
        "Value": 3.0,
        "Sleep Quality": 4.0,
        "Rooms": 5.0,
        "Location": 4.0
      },
      "AuthorLocation": "San Francisco, California",
      "Title": "\u201cA nice place to stay in Napa\u201d",
      "Author": "Rachel L",
      "ReviewID": "UR126923291",
      "Content": "stayed la residence saturday night weekend napa stayed 20 upstairs main house bathroom price average mainly chose 1 night minimum rare napa liked hotel obviously wine cheese reception held 67 nice touch serve hall wine selection cheese raining didnt hot tub looked amazing improvement didnt staff friendly particularly woman breakfast lighting property night improvement nearly fell stairs complete darkness road barely visible driving tofrom parking lot breakfast ok usual costco pastries cereal yogurt definitely stay knowing expect personal touch bb",
      "Date": "2012-03-29 00:00:00"
    },
    {
      "Ratings": {
        "Service": 5.0,
        "Cleanliness": 5.0,
        "Overall": 4.0,
        "Value": 5.0,
        "Sleep Quality": 5.0,
        "Rooms": 5.0,
        "Location": 4.0
      },
      "AuthorLocation": "San Francisco, California",
      "Title": "\u201cBeautiful hotel with fantastic staff\u201d",
      "Author": "Jordanlondon83",
      "ReviewID": "UR126334670",
      "Content": "stayed la residence 1 night stay comfortable cosy bed amazing grounds kept slight issue busy road location easy reach wineries restaurants staff la residence fantastic friendly helpful particularly chris concierge friendly guy sent fantastic restaurants wineries sorted amazing spa massage partner highly recommend la residence value enjoyable napa experience",
      "Date": "2012-03-19 00:00:00"
    },
    {
      "Ratings": {
        "Service": 5.0,
        "Cleanliness": 5.0,
        "Overall": 5.0,
        "Value": 4.0,
        "Sleep Quality": 5.0,
        "Rooms": 4.0,
        "Location": 5.0
      },
      "AuthorLocation": "Menlo Park, California",
      "Title": "\u201cCharming\u201d",
      "Author": "Vix509",
      "ReviewID": "UR124994442",
      "Content": "service cheerful friendly breakfast complimentary cheese wine gathering evening fireplace wonderful linens comfortable kept immaculately location exploring wine",
      "Date": "2012-02-21 00:00:00"
    },
    {
      "Ratings": {
        "Service": 5.0,
        "Cleanliness": 5.0,
        "Overall": 5.0,
        "Value": 5.0,
        "Sleep Quality": 5.0,
        "Rooms": 5.0,
        "Location": 5.0
      },
      "AuthorLocation": "La Pine, Oregon",
      "Title": "\u201cBeautiful Place to Stay\u201d",
      "Author": "Christy N",
      "ReviewID": "UR124451941",
      "Content": "significant stayed hotel weeks ago serene getaways weve sometime cozy antiques bed amazing night sleep ive longtime loved hot tub round close theirs winter staff warm welcoming attentive breakfast serve mornings scrumptious id coffee hot oatmeal 5 stars didnt attend evening wine cheese hour arrived late overall experience la residence staff definitely 5 stars returning guests maybe anniversary destination wedding packages cards future",
      "Date": "2012-02-11 00:00:00"
    },
    {
      "Ratings": {
        "Service": 4.0,
        "Cleanliness": 5.0,
        "Overall": 5.0,
        "Value": 5.0,
        "Sleep Quality": 5.0,
        "Rooms": 5.0,
        "Location": 5.0
      },
      "AuthorLocation": "Los Gatos, CA",
      "Title": "\u201cRelaxing weekend away\u201d",
      "Author": "Elliot F",
      "ReviewID": "UR123925805",
      "Content": "wife decided spend weekend napa quiet peaceful bb rr tis time stayed la residence booked cottage suite separate living relax day wine tasting grounds beautiful complimentary breakfast evening wine tasting excellent",
      "Date": "2012-01-31 00:00:00"
    },
    {
      "Ratings": {
        "Service": 5.0,
        "Cleanliness": 4.0,
        "Overall": 3.0,
        "Value": 3.0,
        "Sleep Quality": 3.0,
        "Rooms": 3.0,
        "Location": 3.0
      },
      "AuthorLocation": "Worthington, Massachusetts",
      "Title": "\u201cCould have been better...\u201d",
      "Author": "Annie L",
      "ReviewID": "UR123796374",
      "Content": "overall pleasant experience lot missed details five star rating arrived smelled fireplace told normal fireplaces normal damper left smell days infused logs burn thank breakfast coffee hot fake cream liquid flavored cream yuk days pastries stale fresh fruit salad solo highlight pastries clean exception carpet dirty bathroom spotless faucets suited sinks water washed toiletries shower awkward climb glass partition fixed sheets quality bed comfortable",
      "Date": "2012-01-29 00:00:00"
    },
    {
      "Ratings": {
        "Service": 5.0,
        "Cleanliness": 5.0,
        "Overall": 5.0,
        "Value": 5.0,
        "Sleep Quality": 5.0,
        "Rooms": 5.0,
        "Location": 5.0
      },
      "AuthorLocation": "Eryka12",
      "Title": "\u201cPerfection\u201d",
      "Author": "Eryka12",
      "ReviewID": "UR122301191",
      "Content": "perfect stay trip staying napa la residence via travelzoo hoped disappointed location close wineries driver didnt spend time traveling hotel wineries staff extremely friendly helpful clean spacious hall wine hour 67 top else nice little buffet breakfast included special job stay surpassed expectations cant wait stay highly recommend hotel",
      "Date": "2011-12-30 00:00:00"
    },
    {
      "Ratings": {
        "Service": 4.0,
        "Cleanliness": 5.0,
        "Overall": 5.0,
        "Value": 4.0,
        "Sleep Quality": 5.0,
        "Rooms": 4.0,
        "Location": 4.0
      },
      "AuthorLocation": "Frisco, Texas",
      "Title": "\u201cGreat Escape\u201d",
      "Author": "Steve W",
      "ReviewID": "UR122044410",
      "Content": "la residence care built relationship staff location wonderful running vineyards morning try burn calories accumulate touring wineries 500 happy hour congregate friends guests heading wonderful dinner recommended hotel friends",
      "Date": "2011-12-23 00:00:00"
    },
    {
      "Ratings": {
        "Service": 5.0,
        "Cleanliness": 5.0,
        "Overall": 5.0,
        "Value": 4.0,
        "Sleep Quality": 5.0,
        "Rooms": 5.0,
        "Location": 5.0
      },
      "AuthorLocation": "San Antonio, Texas",
      "Title": "\u201cWonderful Environment\u201d",
      "Author": "Jim W",
      "ReviewID": "UR121776754",
      "Content": "service staff friendliness ahead hotels visited nation wide quaint inn beautiful surroundings agreat launch wine tour relaxing environment return evening quiet amenities napa visit",
      "Date": "2011-12-15 00:00:00"
    },
    {
      "Ratings": {
        "Service": 5.0,
        "Cleanliness": 5.0,
        "Overall": 5.0,
        "Value": 4.0,
        "Sleep Quality": 5.0,
        "Rooms": 4.0,
        "Location": 5.0
      },
      "AuthorLocation": "Mountain View, California",
      "Title": "\u201cRomantic, elegant & cozy\u201d",
      "Author": "SashaTozzi",
      "ReviewID": "UR121063198",
      "Content": "la residence located middle wine country close distance numerous excellent wineries restaurants ad cozy romantic fireplace ready fired wine tastings 6 pm perfect touch complement nice breakfasts morning staff helpful highly recommend inn",
      "Date": "2011-11-26 00:00:00"
    },
    {
      "Ratings": {
        "Service": 4.0,
        "Cleanliness": 4.0,
        "Overall": 3.0,
        "Value": 3.0,
        "Sleep Quality": 3.0,
        "Rooms": 2.0,
        "Location": 2.0
      },
      "AuthorLocation": "Dallas, Texas",
      "Title": "\u201cBeautiful landscaping and very unique!\u201d",
      "Author": "From_Dallas2",
      "ReviewID": "UR120873931",
      "Content": "spent days recently impressed overall truly unique buildings beautiful landscaping sits grape fields cookie cutter chain hotels exactly chose leaves beginning change pretty overall grounds 4 star unfortunately overall dont wrong nice cant 4 stars based landscaping purchased expected semi private balcony pleasant afternoons bed sheets quality little bit nightstand tables cabinets pretty cheap overall drawers sized gaps bottoms completely fit drawer useless purpose furnishings bit sparse bathroom bathtub unique mosaic tile tub unlike id experienced cracks grout crown molding cracks understand california earthquakes dont expect perfect lot little sample dvd collection nice distraction dont expect top tier selection movies pretty didnt charge pay biggest negative overall physical location highway main drag north town traffic noises wafted ear pretty day night couple fountains running help create white noise minimize wasnt addition fountains night peaceful street noise worse overall definitely nicer experience cookie cutter 3 stars",
      "Date": "2011-11-21 00:00:00"
    },
    {
      "Ratings": {
        "Service": 4.0,
        "Cleanliness": 5.0,
        "Overall": 4.0,
        "Value": 4.0,
        "Sleep Quality": 5.0,
        "Rooms": 4.0,
        "Location": 4.0
      },
      "AuthorLocation": "Edinburgh, United Kingdom",
      "Title": "\u201cQuality In The Sun\u201d",
      "Author": "Ian M",
      "ReviewID": "UR120266206",
      "Content": "sunshine class service napa hour bit north san francisco quaint little gem lies boutique guest house finest properties timber built particularly fine balcony theyre beautifully restored represent bit america trees surround free parking standing alongside grapes vines hens gardens warm welcome awaits arrival little house prairie perfect lovely beds lovely bathrooms lovely toiletries reason theres safe cheese wine served evening wide choice napa grape flavours sit outside verandah watch sun set napa total relaxed breakfasts superb beautiful freshly squeezed juices coffee jams sweetbreads hot griddle middle grounds outside pool dont believe tale heated waters cold pumped baltic refreshing simply freeze entrance drive italian restaurants california bistro don giovanni dine excellent food excellent value busy",
      "Date": "2011-11-07 00:00:00"
    },
    {
      "Ratings": {
        "Service": 3.0,
        "Cleanliness": 3.0,
        "Overall": 3.0,
        "Value": 3.0,
        "Sleep Quality": 2.0,
        "Rooms": 3.0,
        "Location": 3.0
      },
      "AuthorLocation": "Toronto, Canada",
      "Title": "\u201cSo so, would not stay here again\u201d",
      "Author": "Maurizio_and_Jill",
      "ReviewID": "UR120209575",
      "Content": "despite reviews frankly disappointed la residence stay stayed 31 private own entrance nearby hot tub fairly key 1 bed queen extremely uncomfortable soft unsupportive frame creaked toss 2 spot head bed dirty hard reach visible bed oddly angled bit turnoff 3 thermostat programmable hard understand temperature waking cold fireplace logs burn bit waste finally continental breakfast included average selection quality write home horrible stay justified price",
      "Date": "2011-11-05 00:00:00"
    },
    {
      "Ratings": {
        "Service": 5.0,
        "Cleanliness": 5.0,
        "Overall": 5.0,
        "Value": 5.0,
        "Sleep Quality": 5.0,
        "Rooms": 5.0,
        "Location": 4.0
      },
      "AuthorLocation": "Dallas, Texas",
      "Title": "\u201cWonderful weekend in the Wine Country!\u201d",
      "Author": "Randy G",
      "ReviewID": "UR120040035",
      "Content": "review written hotel travel website resist telling terrific weekend weekend la residence country inn wine country firstwe noticed grounds absolutely beautifulthe check simply wonderful beautifully appointed ground floor french doors overlooking outdoor seating intertwined lush landscape own patio beds super comfortable linens feather comforters own fireplace try weather cold morning scrumptious breakfast morning lit breafast featured various fruits cereals breads planning trip wine country seriously consider choosing la residence country inn simply wonderful california experience close spectacular wineries",
      "Date": "2011-11-01 00:00:00"
    },
    {
      "Ratings": {
        "Service": 5.0,
        "Cleanliness": 5.0,
        "Overall": 5.0,
        "Value": 5.0,
        "Sleep Quality": 4.0,
        "Rooms": 4.0,
        "Location": 5.0
      },
      "AuthorLocation": "Seattle",
      "Title": "\u201cCharming with a capital \"C\"\u201d",
      "Author": "k_and_g_from_seattle",
      "ReviewID": "UR118534105",
      "Content": "la residence truly charming beautiful grounds beautiful staff exceptionally friendly provided helpful tips true locals provide nice continental breakfast evening wine hour attracts people easy strike lively discussions wine hour guests nice pool hot tub spa couples families traditional business traveler bonus bistro don giovanni easy walking distance la residence food wine list drive afterwards",
      "Date": "2011-09-24 00:00:00"
    },
    {
      "Ratings": {
        "Service": 5.0,
        "Cleanliness": 5.0,
        "Overall": 4.0,
        "Value": 3.0,
        "Sleep Quality": 5.0,
        "Rooms": 3.0,
        "Location": 5.0
      },
      "AuthorLocation": "Sacramento",
      "Title": "\u201cBeautiful Hotel - Definitely Something Unique\u201d",
      "Author": "RJJ",
      "ReviewID": "UR64608544",
      "Content": "husband stayed hotel bb typical hotel nice stay someplace unique wasnt main instead 3rd floor historic mansion overlooking pool spacious outstanding picky quality ac perfect bathroom normal size bathroom clean excellent downside hot water 10 minutes sink water heat 1015 shower water 5 minutes shower husband lost hot water shower wasnt immediately 30 minutes pool looked nice wasnt heated midmay isnt warm swimming degrees 6pm 9pm mentioned hotel staff hadnt changed shame spa ittoo bad cant heat little hotter guests enjoy breakfast nice loved coffee fruit pastries service confused menu items berry french toast plate didnt realize didnt pick didnt french toast wasnt tasty sort strange combo wheat bread cinnamon berry hash patty deal eggs prepared potatoes excellent probably recommend hotel physical limitations historic mansion stayed elevator carrying stuff 2 flights stairs wasnt time front desk clerk mention night bellman front desk staff guy carrying elses bags car stairs wish front desk staff person mentioned assistance checked 4pm 40s handle physical choose hotel stayed bottom floor main building grounds entire hotel walker wheelchair friendly",
      "Date": "2010-05-18 00:00:00"
    },
    {
      "Ratings": {
        "Service": 5.0,
        "Cleanliness": 5.0,
        "Overall": 5.0,
        "Value": 5.0,
        "Sleep Quality": 5.0,
        "Rooms": 5.0,
        "Location": 5.0
      },
      "AuthorLocation": "Atlanta, Ga",
      "Title": "\u201cExcellent place to relax! Will impress even hard to please clients.\u201d",
      "Author": "Atlanta_Rob",
      "ReviewID": "UR63447841",
      "Content": "am glad found la residence looking business meeting vacation 1520 upper management professionals clients calling napa resorts friend suggested la residence little hesitant book boutique hotel clients checked visitors bureau napa highly recommended hotel hidden hwy 29 napa valley absolutely undiscovered gems surroundings quaint country home touch decadence website don\u00e2\u20ac\u2122t justice nice offer breakfast morning fresh coffee orange juice array fresh fruits wonderful course breakfast finished breakfast found meeting properly setup ready hotel provides free wifi throughout property you\u00e2\u20ac\u2122re close office nice pool hot tub property cooling relaxing clean care grounds kept picturesque maintained beds comfortable slept la residence own bed meetings day napa returned clean tidy 600pm met daily complementary wine cheese hour found exquisite selection cheeses hot delicacies day relaxing wind day heading napa dinner week experience exceptional moment checked relaxed home nice meeting space provided technology hold meeting food beverage services food esthetic presentation rate impressed unique boutique hotel couldn\u00e2\u20ac\u2122t hotel absolutely delightful accommodating provided personal service level professionalism don\u00e2\u20ac\u2122t garden variety hotel chain hotels found exceptional value quality service thanks la residence we\u00e2\u20ac\u2122ll",
      "Date": "2010-05-06 00:00:00"
    },
    {
      "Ratings": {
        "Service": 5.0,
        "Cleanliness": 5.0,
        "Overall": 5.0,
        "Value": 5.0,
        "Sleep Quality": 5.0,
        "Rooms": 5.0,
        "Location": 5.0
      },
      "AuthorLocation": "Vancouver, Washington",
      "Title": "\u201cExceptional service, value, and great food as part of the room. Nice!\u201d",
      "Author": "CATravelWest",
      "ReviewID": "UR63176260",
      "Content": "hall winner service staff excellent clean comfortable bed convenient location hot breakfast evening wine cheese event bonus staff excellent alana sales extra mile location albeit hwy 29 feel country estate enjoyed complimentary wine bottled water placed thanks value feel home",
      "Date": "2010-05-04 00:00:00"
    },
    {
      "Ratings": {
        "Service": 5.0,
        "Cleanliness": 5.0,
        "Overall": 5.0,
        "Value": 5.0,
        "Sleep Quality": 5.0,
        "Rooms": 4.0,
        "Location": 4.0
      },
      "AuthorLocation": "Seattle",
      "Title": "\u201cExcellent service, homey comforts, central location\u201d",
      "Author": "JennyBSeattle",
      "ReviewID": "UR55389686",
      "Content": "husband la residence extended weekend celebrate 40th birthday lovely time highlights service wonderful helpful cheerful bed comfortable leave complimentary cookedtoorder breakfast start day wine appetizer reception evening grounds beautiful highway drive wouldnt fireplace nice tips series main building main walkway zero privacy dont reserve salon suite id originally reserved wraparound porch fabulous summer fireplace staff graciously change suite fireplace bistro don giovanni road definitely worth dinner bustling atmosphere fabulous food",
      "Date": "2010-02-07 00:00:00"
    }
  ],
  "HotelInfo": {
    "Name": "La Residence",
    "HotelURL": "/ShowUserReviews-g32766-d190271-Reviews-La_Residence-Napa_Napa_Valley_California.html",
    "Price": "$247 - $394*",
    "Address": "<address><span rel=\"v:address\"><span dir=\"ltr\"><span class=\"street-address\" property=\"v:street-address\">4066 Howard Lane</span>, <span class=\"locality\"><span property=\"v:locality\">Napa</span>, <span property=\"v:region\">CA</span> <span property=\"v:postal-code\">94558</span></span> </span></span></address>",
    "HotelID": "190271",
    "ImgURL": "http://media-cdn.tripadvisor.com/media/photo-s/02/25/6f/7d/ponds-on-property.jpg"
  }
}