{
  "Reviews": [
    {
      "Ratings": {
        "Service": 4.0,
        "Cleanliness": 4.0,
        "Overall": 4.0,
        "Value": 4.0,
        "Sleep Quality": 4.0,
        "Rooms": 3.0,
        "Location": 4.0
      },
      "AuthorLocation": "Nottingham, England, United Kingdom",
      "Title": "\u201cBest Western Trafalgar Madrid\u201d",
      "Author": "Philip S",
      "ReviewID": "UR128573688",
      "Content": "stayed night prior leaving airport morning booked single smoking contained expect 3 star hotel 7th floor advantage balcony views city bathroom clean equipt toiletries arrived sunday evening bar closed hey plenty nearby eat hotel time factors dining look pleasant satff friendly welcoming helpful",
      "Date": "2012-04-25 00:00:00"
    },
    {
      "Ratings": {
        "Service": 5.0,
        "Cleanliness": 4.0,
        "Overall": 4.0,
        "Value": 3.0,
        "Sleep Quality": 4.0,
        "Rooms": 4.0,
        "Location": 4.0
      },
      "AuthorLocation": "Marseille, France",
      "Title": "\u201cGood hotel, courteous service.\u201d",
      "Author": "jonnym127",
      "ReviewID": "UR125720942",
      "Content": "clean kept hotel courteous staff stayed six nights hotel metro stations easy easily city madrid rate reasonable 86 euros night double bed quiet breakfast included worth paying 540 euros person quality breakfast",
      "Date": "2012-03-06 00:00:00"
    },
    {
      "Ratings": {
        "Service": 4.0,
        "Cleanliness": 4.0,
        "Overall": 4.0,
        "Value": 4.0,
        "Sleep Quality": 4.0,
        "Rooms": 4.0,
        "Location": 3.0
      },
      "AuthorLocation": "Alford, Lincolnshire",
      "Title": "\u201cGood Value Hotel\u201d",
      "Author": "JamesV92",
      "ReviewID": "UR125459109",
      "Content": "value hotel neighborhood madrid stayed cost \u20ac60 affordable option watch real madrid bernabeu hotel centre city close metro stations offer quick links airport major attractions supermarket shops nearby reasonable choice restaurants stayed quality bed comfortable particularly impressed quality cleanliness bathroom",
      "Date": "2012-03-01 00:00:00"
    },
    {
      "Ratings": {
        "Service": 5.0,
        "Cleanliness": 5.0,
        "Overall": 5.0,
        "Value": 5.0,
        "Sleep Quality": 5.0,
        "Rooms": 5.0,
        "Location": 5.0
      },
      "AuthorLocation": "Salamanca, Spain",
      "Title": "\u201cHotel en Chamberi\u201d",
      "Author": "supersabio",
      "ReviewID": "UR123698270",
      "Content": "hotel situated 50 metres plaza de madrids hidden treasures surrounding streets delightful bars restaurantsthe hotel close metro stations hotel managed welcoming helpful reception equiped",
      "Date": "2012-01-27 00:00:00"
    },
    {
      "Ratings": {
        "Service": 3.0,
        "Cleanliness": 4.0,
        "Overall": 3.0,
        "Value": 4.0,
        "Sleep Quality": 3.0,
        "Rooms": 2.0,
        "Location": 4.0
      },
      "AuthorLocation": "Coventry",
      "Title": "\u201cGood Hotel in Downtown\u201d",
      "Author": "EngineerCoventry",
      "ReviewID": "UR120299080",
      "Content": "clean modern minutes walk metro stations english channel tv cnn staff friendly helpful noise adjacent disturb occasionally pay \u20ac1 time safe expensive service apart breakfast restaurant weekends plenty cafes nearby stay",
      "Date": "2011-11-07 00:00:00"
    },
    {
      "Ratings": {
        "Service": 5.0,
        "Cleanliness": 5.0,
        "Overall": 5.0,
        "Value": 5.0,
        "Sleep Quality": 3.0,
        "Rooms": 4.0,
        "Location": 5.0
      },
      "AuthorLocation": "Chicago",
      "Title": "\u201cCheap hotel in Madrid downtown\u201d",
      "Author": "igorek",
      "ReviewID": "UR119813762",
      "Content": "night stay sleep amazed expediacom special rate 57 including taxes breakfast clean simple decor nice friendly knowledgeable staff escorted shown arrival free wifi slow drawback paper thin walls earplugs neighborhood lot barsclubs etc couple minutes subway",
      "Date": "2011-10-27 00:00:00"
    },
    {
      "Ratings": {
        "Service": 4.0,
        "Cleanliness": 4.0,
        "Overall": 4.0,
        "Value": 4.0,
        "Sleep Quality": 4.0,
        "Rooms": 4.0,
        "Location": 4.0
      },
      "AuthorLocation": "Rocky Point, New York",
      "Title": "\u201cvery modern and clean\u201d",
      "Author": "irisheyes67_11",
      "ReviewID": "UR119638495",
      "Content": "stayed 1 night hotel central location cleanmodern staff friendly fluent english downstairs hosts cafe basically continental style breakfast hard cooked cheese pastries toast coffee amazing time 2011 price 6 euro baths clean modern beds free wifi plus",
      "Date": "2011-10-23 00:00:00"
    },
    {
      "Ratings": {
        "Service": 3.0,
        "Cleanliness": 5.0,
        "Overall": 4.0,
        "Value": 5.0,
        "Sleep Quality": 4.0,
        "Rooms": 3.0,
        "Location": 5.0
      },
      "AuthorLocation": "Vienna, Austria",
      "Title": "\u201cValue for money, good option in Madrid\u201d",
      "Author": "schaefer1010",
      "ReviewID": "UR89416588",
      "Content": "trafalgar residential madrid close nice plaza metro stations walking distance lots restaurants bars arround basic clean efficiently equipped dont expect breakfast coffee terrible bars arround complained lift persons",
      "Date": "2010-12-09 00:00:00"
    },
    {
      "Ratings": {
        "Service": 4.0,
        "Cleanliness": 4.0,
        "Overall": 4.0,
        "Value": 4.0,
        "Sleep Quality": 4.0,
        "Rooms": 3.0,
        "Location": 4.0
      },
      "AuthorLocation": "Brisbane, Australia",
      "Title": "\u201cThis hotel provided great value and excellent service.\u201d",
      "Author": "michaelpom",
      "ReviewID": "UR81600142",
      "Content": "arrival diligent porter carried reception checkin bathroom clean appointed comfortable balcony looked onto relatively street day hot airconditioning effectively internet connection available reasonable cost breakfast included overall cost excellent value",
      "Date": "2010-09-30 00:00:00"
    }
  ],
  "HotelInfo": {
    "Name": "BEST WESTERN Hotel Trafalgar",
    "HotelURL": "/ShowUserReviews-g187514-d232808-Reviews-BEST_WESTERN_Hotel_Trafalgar-Madrid.html",
    "Price": "$72 and up*",
    "Address": "<address><span rel=\"v:address\"><span dir=\"ltr\"><span class=\"street-address\" property=\"v:street-address\">Trafalgar 35</span>, <span class=\"locality\"><span property=\"v:postal-code\">28010</span> <span property=\"v:locality\">Madrid</span></span>, <span class=\"country-name\" property=\"v:country-name\">Spain</span> </span></span></address>",
    "HotelID": "232808",
    "ImgURL": "http://media-cdn.tripadvisor.com/media/ProviderThumbnails/dirs/c1/7f/c17faa1e9829a3fb339f6deed895732c5large.jpg"
  }
}