{
  "Reviews": [
    {
      "Ratings": {
        "Service": 1.0,
        "Cleanliness": 1.0,
        "Overall": 1.0,
        "Value": 3.0,
        "Sleep Quality": 1.0,
        "Rooms": 1.0,
        "Location": 3.0
      },
      "AuthorLocation": "Waterford, Canada",
      "Title": "\u201cWaste of Time!!!!\u201d",
      "Author": "Joanne L",
      "ReviewID": "UR122639591",
      "Content": "absolute worst hotel experience hotel sad repair foundation looked disgusting police called drunk control guests parties check key key quiet refunded money told trouble staff extremely rude waiting 4 hours check staff loudly lobby guests told hotel foreclosure allowed limited staff excuse checked clock stuck 300 shift change staff late ruder 1st recommend attempt stay definately feel safe glad money refunded experience interior",
      "Date": "2012-01-06 00:00:00"
    },
    {
      "Ratings": {
        "Service": 3.0,
        "Cleanliness": 3.0,
        "Overall": 4.0,
        "Value": 3.0,
        "Sleep Quality": 4.0,
        "Rooms": 3.0,
        "Location": 3.0
      },
      "AuthorLocation": "london",
      "Title": "\u201cwhat you pay for\u201d",
      "Author": "k g",
      "ReviewID": "UR120976028",
      "Content": "remember pay fine maingate journey disney posh pay adequate disney stay time",
      "Date": "2011-11-23 00:00:00"
    },
    {
      "Ratings": {
        "Service": 1.0,
        "Cleanliness": 1.0,
        "Overall": 1.0,
        "Value": 1.0,
        "Sleep Quality": 1.0,
        "Rooms": 1.0,
        "Location": 5.0
      },
      "AuthorLocation": "Niagara Falls, New York",
      "Title": "\u201cCan't believe Day's Inn lets this place carry it's name!!\u201d",
      "Author": "lorimessing",
      "ReviewID": "UR109792428",
      "Content": "party eight including children requested connecting day disney checked 1030 pm connecting fine pulled bedspread blanket childrens beds glitter lint called front dest request sheets told housekeeping gone night set kidding else couldnt gotten taking sheets bed sleeping top bedspread night dressed bathrooms disgusting peeling paint wall paper bugs lights vents hair else air conditioner shut unplugged phone wouldnt stop beeping apparantly message unplugged volume button tv didnt smelled musty pool taped reason worst initial walk poolside meant walk past inner corridor paint peeling doors passing particular drapes pushed window stains looked murdered welcoming sight morning called manager duty requested told busy sent housekeeping friendly apologetic guided complaint list told owner recently cut told stained drapes storage look eyes guest agreed bad checking cancelling nights stay corporate office phone told wouldnt matter hotel independently owned contacted anyways told franchisee maintain days inn standards risk losing franchise luck booked disney clean usable pool restaurants actually late wonderful activities children absolutely reccommend warn stay re pictures proof management team requsted busy look",
      "Date": "2011-05-25 00:00:00"
    },
    {
      "Ratings": {
        "Service": 3.0,
        "Cleanliness": 3.0,
        "Overall": 2.0,
        "Value": 1.0,
        "Sleep Quality": 3.0,
        "Rooms": 2.0,
        "Location": 4.0
      },
      "AuthorLocation": "Coquitlam, BC",
      "Title": "\u201cNot worth it\u201d",
      "Author": "RobCoquitlam_BC",
      "ReviewID": "UR105267610",
      "Content": "days inns usually properties definitely budget orientated didnt expect arrival night clerk service orientated doorlock didnt function maintenance couldnt supposed definitely liked downhill wireless internet didnt building advertised daybreak breakfast available sheets wrong size bed fitted double sheet queen issues booking days inn website doesnt listed anymore hmmmm question recommend pass",
      "Date": "2011-04-24 00:00:00"
    },
    {
      "Ratings": {
        "Service": 3.0,
        "Cleanliness": 1.0,
        "Overall": 1.0,
        "Value": 1.0,
        "Sleep Quality": 1.0,
        "Rooms": 1.0,
        "Location": 4.0
      },
      "AuthorLocation": "ND",
      "Title": "\u201cDisgusting!\u201d",
      "Author": "NdExplorer",
      "ReviewID": "UR102573633",
      "Content": "trip disneyworld family including children 36night rate attractive photos website wed found deal wrong drove checkin initially closed joked condemned front lobby rundown worn late decided chances walked kids horrid look drive hours orlando stay smelled looked itd carpets cleaned morning complained bugs crawling faucet bedbug bites smell mold pool closed brown tint kitchen closed dont believe photos website couldnt leave fast",
      "Date": "2011-04-02 00:00:00"
    },
    {
      "Ratings": {
        "Service": 2.0,
        "Cleanliness": 2.0,
        "Overall": 2.0,
        "Value": 3.0,
        "Sleep Quality": 3.0,
        "Rooms": 3.0,
        "Location": 5.0
      },
      "AuthorLocation": "Cheshire uk",
      "Title": "\u201cWe was there 10 days no clean bedding, room or bathroom wasnt cleaned,once\u201d",
      "Author": "pen64d",
      "ReviewID": "UR79423705",
      "Content": "smelly toilet loose resturant closed gift shop bar pool gone pool dirty dead insects edge shade pool life guard checked owed 38 dont check refused pay location fantastic door town close resturants bars",
      "Date": "2010-09-13 00:00:00"
    },
    {
      "Ratings": {
        "Service": 5.0,
        "Cleanliness": 5.0,
        "Overall": 4.0,
        "Value": 5.0,
        "Sleep Quality": 5.0,
        "Rooms": 5.0,
        "Location": 5.0
      },
      "AuthorLocation": "kissimmee florida",
      "Title": "\u201cAffordable play to stay\u201d",
      "Author": "rwarfield",
      "ReviewID": "UR68597709",
      "Content": "clean service wonderful carlo wonderful love staff cleaning women internet ok price affordable clean staff helpful",
      "Date": "2010-06-24 00:00:00"
    },
    {
      "Ratings": {
        "Service": 3.0,
        "Cleanliness": 3.0,
        "Overall": 3.0,
        "Value": 4.0,
        "Sleep Quality": 3.0,
        "Rooms": 3.0,
        "Location": 4.0
      },
      "AuthorLocation": "00784",
      "Title": "\u201cGood for your Budget\u201d",
      "Author": "Frugalvalen",
      "ReviewID": "UR54957912",
      "Content": "hotel hotel budget paid close town action park report keys due humidity water 2 hours due overall hotel bargain family budget",
      "Date": "2010-02-01 00:00:00"
    }
  ],
  "HotelInfo": {
    "Name": "Days Inn Maingate East",
    "HotelURL": "/ShowUserReviews-g34352-d84702-Reviews-Days_Inn_Maingate_East-Kissimmee_Florida.html",
    "Price": "$41 - $56*",
    "Address": "<address><span rel=\"v:address\"><span dir=\"ltr\"><span class=\"street-address\" property=\"v:street-address\">5840 West Irlo Bronson Memorial Highway</span>, <span class=\"locality\"><span property=\"v:locality\">Kissimmee</span>, <span property=\"v:region\">FL</span> <span property=\"v:postal-code\">34746</span></span> </span></span></address>",
    "HotelID": "84702",
    "ImgURL": "http://media-cdn.tripadvisor.com/media/ProviderThumbnails/dirs/15/ec/15ece58cff7eb123c9e92ea2291d59451large.jpg"
  }
}